sbvt/__init__.py
sbvt/api.py
sbvt/app.py
sbvt/browser.py
sbvt/imagetools.py
sbvt/timer.py
sbvt/visualtest.py
visualtest_python-1.9.6.dist-info/licenses/LICENSE
visualtest_python-1.9.6.dist-info/METADATA
visualtest_python-1.9.6.dist-info/WHEEL
visualtest_python-1.9.6.dist-info/top_level.txt
visualtest_python-1.9.6.dist-info/RECORD
