Metadata-Version: 2.4
Name: visualtest-python
Version: 1.9.6
Summary: Python SDK for SmartBear VisualTest via Selenium WebDriver
Home-page: https://github.com/SmartBear/visualtest-python
Author: Luke Kende
Author-email: luke.kende@smartbear.com
Keywords: visual testing,UI testing,GUI testing,UX testing,screenshots,full page screenshots,image comparisons,regression testing
Classifier: Development Status :: 5 - Production/Stable
Classifier: Environment :: Web Environment
Classifier: Intended Audience :: Developers
Classifier: Intended Audience :: Information Technology
Classifier: Operating System :: OS Independent
Classifier: Programming Language :: Python :: 3
Classifier: License :: OSI Approved :: MIT License
License-File: LICENSE
Requires-Dist: requests
Requires-Dist: Pillow
Requires-Dist: numpy
Requires-Dist: python-dotenv
Requires-Dist: packaging
Requires-Dist: colorama
Requires-Dist: colour
Requires-Dist: axe-selenium-python
Dynamic: description
Dynamic: description-content-type
Dynamic: license-file
